wstring/Exceptions.py
wstring/__init__.py
wstring/wstring.py
wstring-1.0.3.dist-info/LICENSE
wstring-1.0.3.dist-info/METADATA
wstring-1.0.3.dist-info/WHEEL
wstring-1.0.3.dist-info/entry_points.txt
wstring-1.0.3.dist-info/top_level.txt
wstring-1.0.3.dist-info/RECORD
