Metadata-Version: 2.1
Name: wstring
Version: 1.0.3
Summary: A library to print a welcome message in patterns
Home-page: https://github.com/TONYSTARK-EDITH/Welcome_String
Author: Tony Stark
Author-email: manthirajak@gmail.com
License: UNKNOWN
Keywords: Welcome String,python,terminal
Platform: UNKNOWN
Classifier: Programming Language :: Python :: 3
Classifier: License :: OSI Approved :: MIT License
Classifier: Operating System :: OS Independent
Requires-Python: >=3.0
Requires-Dist: colorama
Requires-Dist: termcolor
